nornir/__init__.py
nornir/core/__init__.py
nornir/core/configuration.py
nornir/core/exceptions.py
nornir/core/filter.py
nornir/core/helpers/__init__.py
nornir/core/helpers/jinja_helper.py
nornir/core/inventory.py
nornir/core/plugins/__init__.py
nornir/core/plugins/connections.py
nornir/core/plugins/inventory.py
nornir/core/plugins/register.py
nornir/core/plugins/runners.py
nornir/core/processor.py
nornir/core/state.py
nornir/core/task.py
nornir/init_nornir.py
nornir/plugins/__init__.py
nornir/plugins/connections/__init__.py
nornir/plugins/functions/__init__.py
nornir/plugins/inventory/__init__.py
nornir/plugins/inventory/simple.py
nornir/plugins/processors/__init__.py
nornir/plugins/runners/__init__.py
nornir/plugins/tasks/__init__.py
nornir/py.typed
nornir-3.4.0.dist-info/LICENSE
nornir-3.4.0.dist-info/METADATA
nornir-3.4.0.dist-info/WHEEL
nornir-3.4.0.dist-info/entry_points.txt
nornir-3.4.0.dist-info/RECORD
