Metadata-Version: 2.1
Name: nornir
Version: 3.4.0
Summary: Pluggable multi-threaded framework with inventory management to help operate collections of devices
Home-page: https://github.com/nornir-automation/nornir
License: Apache 2.0
Author: David Barroso
Author-email: dbarrosop@dravetech.com
Requires-Python: >=3.8,<4.0
Classifier: License :: OSI Approved :: Apache Software License
Classifier: License :: Other/Proprietary License
Classifier: Programming Language :: Python :: 3
Classifier: Programming Language :: Python :: 3.8
Classifier: Programming Language :: Python :: 3.9
Classifier: Programming Language :: Python :: 3.10
Classifier: Programming Language :: Python :: 3.11
Requires-Dist: importlib-metadata (>=4,<5) ; python_version < "3.10"
Requires-Dist: ruamel.yaml (>=0.17)
Project-URL: Repository, https://github.com/nornir-automation/nornir
